datatonic_pipeline_components/__init__.py
datatonic_pipeline_components/gpt_tokenize/.dockerignore
datatonic_pipeline_components/gpt_tokenize/Dockerfile
datatonic_pipeline_components/gpt_tokenize/README.md
datatonic_pipeline_components/gpt_tokenize/gpt_tokenize/__init__.py
datatonic_pipeline_components/gpt_tokenize/gpt_tokenize/component.py
datatonic_pipeline_components/gpt_tokenize/gpt_tokenize/component.yaml
datatonic_pipeline_components/gpt_tokenize/kfp_config.ini
datatonic_pipeline_components/gpt_tokenize/poetry.lock
datatonic_pipeline_components/gpt_tokenize/pyproject.toml
datatonic_pipeline_components/gpt_tokenize/tests/__init__.py
datatonic_pipeline_components/gpt_tokenize/tests/test_gpt_tokenize.py
datatonic_pipeline_components/load_huggingface_tensorflow/.dockerignore
datatonic_pipeline_components/load_huggingface_tensorflow/Dockerfile
datatonic_pipeline_components/load_huggingface_tensorflow/README.md
datatonic_pipeline_components/load_huggingface_tensorflow/kfp_config.ini
datatonic_pipeline_components/load_huggingface_tensorflow/load_huggingface_tensorflow/component.py
datatonic_pipeline_components/load_huggingface_tensorflow/load_huggingface_tensorflow/component.yaml
datatonic_pipeline_components/load_huggingface_tensorflow/load_huggingface_tensorflow/tests/__init__.py
datatonic_pipeline_components/load_huggingface_tensorflow/load_huggingface_tensorflow/tests/test_component.py
datatonic_pipeline_components/load_huggingface_tensorflow/poetry.lock
datatonic_pipeline_components/load_huggingface_tensorflow/pyproject.toml
datatonic_pipeline_components/load_huggingface_torch/.dockerignore
datatonic_pipeline_components/load_huggingface_torch/Dockerfile
datatonic_pipeline_components/load_huggingface_torch/README.md
datatonic_pipeline_components/load_huggingface_torch/kfp_config.ini
datatonic_pipeline_components/load_huggingface_torch/load_huggingface_torch/component.py
datatonic_pipeline_components/load_huggingface_torch/load_huggingface_torch/component.yaml
datatonic_pipeline_components-1.1.1.dist-info/METADATA
datatonic_pipeline_components-1.1.1.dist-info/WHEEL
datatonic_pipeline_components-1.1.1.dist-info/RECORD
