Metadata-Version: 2.1
Name: datatonic-pipeline-components
Version: 1.1.1
Summary: KFP components developed at Datatonic
Author: Eugene Brown
Author-email: eugene.brown@datatonic.com
Requires-Python: >=3.8,<3.12
Classifier: Programming Language :: Python :: 3
Classifier: Programming Language :: Python :: 3.8
Classifier: Programming Language :: Python :: 3.9
Classifier: Programming Language :: Python :: 3.10
Classifier: Programming Language :: Python :: 3.11
Requires-Dist: kfp[all] (>=2.0.1,<3.0.0)
